resqml22/__init__.py
resqml22/absolute_pressure.py
resqml22/absolute_pressure_interval.py
resqml22/absorbed_dose_measure.py
resqml22/absorbed_dose_measure_ext.py
resqml22/absorbed_dose_uom.py
resqml22/abstract2d_crs.py
resqml22/abstract2d_position.py
resqml22/abstract3d_position.py
resqml22/abstract_active_object.py
resqml22/abstract_activity_parameter.py
resqml22/abstract_boolean_array.py
resqml22/abstract_cartesian2d_position.py
resqml22/abstract_color_map.py
resqml22/abstract_column_layer_grid_geometry.py
resqml22/abstract_column_layer_grid_representation.py
resqml22/abstract_compound_crs.py
resqml22/abstract_compound_position.py
resqml22/abstract_contact_interpretation_part.py
resqml22/abstract_elevation.py
resqml22/abstract_feature.py
resqml22/abstract_feature_interpretation.py
resqml22/abstract_floating_point_array.py
resqml22/abstract_geographic2d_crs.py
resqml22/abstract_geologic_unit_organization_interpretation.py
resqml22/abstract_geometry.py
resqml22/abstract_graphical_information.py
resqml22/abstract_graphical_information_for_indexable_element.py
resqml22/abstract_grid_geometry.py
resqml22/abstract_grid_representation.py
resqml22/abstract_growing_object.py
resqml22/abstract_growing_object_part.py
resqml22/abstract_horizontal_coordinates.py
resqml22/abstract_integer_array.py
resqml22/abstract_interval.py
resqml22/abstract_md_growing_object.py
resqml22/abstract_md_growing_part.py
resqml22/abstract_md_interval_growing_part.py
resqml22/abstract_numeric_array.py
resqml22/abstract_object.py
resqml22/abstract_organization_interpretation.py
resqml22/abstract_parameter_key.py
resqml22/abstract_parametric_line_array.py
resqml22/abstract_parametric_line_geometry.py
resqml22/abstract_parent_window.py
resqml22/abstract_plane_geometry.py
resqml22/abstract_point3d_array.py
resqml22/abstract_position.py
resqml22/abstract_pressure_interval.py
resqml22/abstract_pressure_value.py
resqml22/abstract_projected_crs.py
resqml22/abstract_property.py
resqml22-1.0.0.dist-info/LICENSE
resqml22-1.0.0.dist-info/WHEEL
resqml22-1.0.0.dist-info/METADATA
resqml22-1.0.0.dist-info/RECORD
